.DS_Store
patgen/__init__.py
patgen/chunker.py
patgen/dictionary.py
patgen/hyphenate.py
patgen/layer.py
patgen/main.py
patgen/margins.py
patgen/patternset.py
patgen/problem.py
patgen/project.py
patgen/range.py
patgen/selector.py
patgen/suffix_array.py
patgen/validate.py
patgen/version.py
pypatgen-0.2.9.dist-info/DESCRIPTION.rst
pypatgen-0.2.9.dist-info/entry_points.txt
pypatgen-0.2.9.dist-info/METADATA
pypatgen-0.2.9.dist-info/metadata.json
pypatgen-0.2.9.dist-info/RECORD
pypatgen-0.2.9.dist-info/top_level.txt
pypatgen-0.2.9.dist-info/WHEEL
