Metadata-Version: 2.0
Name: pypatgen
Version: 0.2.9
Summary: TeX hyphenation pattern generator
Home-page: https://github.com/pgmmpk/pypatgen
Author: Mike Kroutikov
Author-email: pgmmpk@gmail.com
License: MIT
Keywords: TeX hyphenation
Platform: UNKNOWN
Classifier: Development Status :: 4 - Beta
Classifier: License :: OSI Approved :: MIT License
Classifier: Programming Language :: Python :: 2.7
Classifier: Programming Language :: Python :: 3
